_libdnf5_shim/__init__.py
_libdnf5_shim/_impl.py
_libdnf5_shim/initialize.py
_libdnf5_shim/initialize_cli.py
libdnf5.py
libdnf5_cli.py
libdnf5_shim-0.1.0.dist-info/METADATA
libdnf5_shim-0.1.0.dist-info/WHEEL
libdnf5_shim-0.1.0.dist-info/licenses/LICENSES/MIT.txt
libdnf5_shim-0.1.0.dist-info/RECORD
